tatiana/__init__.py
tatiana/entity.py
tatiana/typenames.py
tatiana/world.py
tatiana-0.0.2.1.dist-info/LICENSE
tatiana-0.0.2.1.dist-info/METADATA
tatiana-0.0.2.1.dist-info/WHEEL
tatiana-0.0.2.1.dist-info/top_level.txt
tatiana-0.0.2.1.dist-info/RECORD
