Metadata-Version: 2.1
Name: tatiana
Version: 0.0.2.1
Summary: Un pobre intento de hacer un pequeño motor de videojuegos utilizando Python (≥ 3.10) y pygame
Author-email: Alonzo Ximénez Qui <alonzo.ximenez.qui@gmail.com>
Project-URL: Homepage, https://soyeltata.github.io/tatiana/
Project-URL: Bug Tracker, https://github.com/soyeltata/tatiana/issues
Classifier: Programming Language :: Python :: 3
Classifier: License :: OSI Approved :: GNU General Public License v3 (GPLv3)
Classifier: Operating System :: OS Independent
Requires-Python: >=3.10
License-File: LICENSE
Requires-Dist: pygame
